HbuilderShiyongJiaocheng/README.md
HbuilderShiyongJiaocheng/__init__.py
HbuilderShiyongJiaocheng/__main__.py
HbuilderShiyongJiaocheng/file.epub
HbuilderShiyongJiaocheng/index.html
HbuilderShiyongJiaocheng/css/__init__.py
HbuilderShiyongJiaocheng/css/annotations.css
HbuilderShiyongJiaocheng/css/main.css
HbuilderShiyongJiaocheng/css/normalize.css
HbuilderShiyongJiaocheng/css/popup.css
HbuilderShiyongJiaocheng/font/__init__.py
HbuilderShiyongJiaocheng/font/fontello.eot
HbuilderShiyongJiaocheng/font/fontello.svg
HbuilderShiyongJiaocheng/font/fontello.ttf
HbuilderShiyongJiaocheng/font/fontello.woff
HbuilderShiyongJiaocheng/img/__init__.py
HbuilderShiyongJiaocheng/img/annotator-glyph-sprite.png
HbuilderShiyongJiaocheng/img/annotator-icon-sprite.png
HbuilderShiyongJiaocheng/img/apple-touch-icon.png
HbuilderShiyongJiaocheng/img/cancelfullscreen.png
HbuilderShiyongJiaocheng/img/close.png
HbuilderShiyongJiaocheng/img/fullscreen.png
HbuilderShiyongJiaocheng/img/loader.gif
HbuilderShiyongJiaocheng/img/menu-icon.png
HbuilderShiyongJiaocheng/img/save.png
HbuilderShiyongJiaocheng/img/saved.png
HbuilderShiyongJiaocheng/img/settings-s.png
HbuilderShiyongJiaocheng/img/settings.png
HbuilderShiyongJiaocheng/img/star.png
HbuilderShiyongJiaocheng/js/__init__.py
HbuilderShiyongJiaocheng/js/epub.js
HbuilderShiyongJiaocheng/js/epub.min.js
HbuilderShiyongJiaocheng/js/epub.min.map
HbuilderShiyongJiaocheng/js/hooks.min.js
HbuilderShiyongJiaocheng/js/hooks.min.map
HbuilderShiyongJiaocheng/js/reader.js
HbuilderShiyongJiaocheng/js/reader.js.map
HbuilderShiyongJiaocheng/js/reader.min.js
HbuilderShiyongJiaocheng/js/reader.min.map
HbuilderShiyongJiaocheng/js/hooks/__init__.py
HbuilderShiyongJiaocheng/js/hooks/extensions/__init__.py
HbuilderShiyongJiaocheng/js/hooks/extensions/highlight.js
HbuilderShiyongJiaocheng/js/libs/__init__.py
HbuilderShiyongJiaocheng/js/libs/jquery.min.js
HbuilderShiyongJiaocheng/js/libs/localforage.min.js
HbuilderShiyongJiaocheng/js/libs/screenfull.js
hbuilder_shiyong_jiaocheng-2024.3.2.0.dist-info/METADATA
hbuilder_shiyong_jiaocheng-2024.3.2.0.dist-info/WHEEL
hbuilder_shiyong_jiaocheng-2024.3.2.0.dist-info/entry_points.txt
hbuilder_shiyong_jiaocheng-2024.3.2.0.dist-info/top_level.txt
hbuilder_shiyong_jiaocheng-2024.3.2.0.dist-info/RECORD
